<annotation>
	<folder>images</folder>
	<filename>mask-142.jpg</filename>
	<path>C:\Users\kuick\OneDrive\Desktop\Yr 3\ATA\mask_project\data\images\mask-142.jpg</path>
	<source>
		<database>Unknown</database>
	</source>
	<size>
		<width>3744</width>
		<height>5616</height>
		<depth>3</depth>
	</size>
	<segmented>0</segmented>
	<object>
		<name>person</name>
		<pose>Unspecified</pose>
		<truncated>1</truncated>
		<difficult>0</difficult>
		<bndbox>
			<xmin>272</xmin>
			<ymin>655</ymin>
			<xmax>3744</xmax>
			<ymax>5616</ymax>
		</bndbox>
	</object>
	<object>
		<name>mask</name>
		<pose>Unspecified</pose>
		<truncated>0</truncated>
		<difficult>0</difficult>
		<bndbox>
			<xmin>603</xmin>
			<ymin>2305</ymin>
			<xmax>2891</xmax>
			<ymax>4255</ymax>
		</bndbox>
	</object>
</annotation>
